authorization_hero/__init__.py
authorization_hero/authorizer.py
authorization_hero-0.1.1.dist-info/LICENSE
authorization_hero-0.1.1.dist-info/METADATA
authorization_hero-0.1.1.dist-info/WHEEL
authorization_hero-0.1.1.dist-info/RECORD
