Metadata-Version: 2.1
Name: authorization-hero
Version: 0.1.1
Summary: Authorization in Flask
License: MIT
Keywords: flask,authorization
Author: DukeOfRI
Requires-Python: >=3.11,<4.0
Classifier: License :: OSI Approved :: MIT License
Classifier: Programming Language :: Python :: 3
Classifier: Programming Language :: Python :: 3.11
Classifier: Programming Language :: Python :: 3.12
